LDI/Compare_Resonance.py
LDI/DataDirectories.json
LDI/DataImportSettings.json
LDI/LDI.py
LDI/LumericalDataImport.py
LDI/TestSetup.py
LDI/__init__.py
LDI_DeltaMod-0.0.5.data/scripts/LDI.py
LDI_DeltaMod-0.0.5.dist-info/LICENSE
LDI_DeltaMod-0.0.5.dist-info/METADATA
LDI_DeltaMod-0.0.5.dist-info/WHEEL
LDI_DeltaMod-0.0.5.dist-info/top_level.txt
LDI_DeltaMod-0.0.5.dist-info/RECORD
