Metadata-Version: 2.1
Name: LDI-DeltaMod
Version: 0.0.5
Summary: This is an Example Package
Home-page: https://github.com/DeltaMod/LDI
Author: Atli Vidar Már FLodgren
Author-email: vidar.flodgren@sljus.lu.se
License: UNKNOWN
Keywords: hello world example examples
Platform: UNKNOWN
Classifier: Programming Language :: Python :: 3
Classifier: License :: OSI Approved :: GNU General Public License v3 (GPLv3)
Classifier: Operating System :: OS Independent
Classifier: Development Status :: 2 - Pre-Alpha
Requires-Dist: numpy
Requires-Dist: scipy
Requires-Dist: natsort
Requires-Dist: hdf5storage
Requires-Dist: matplotlib
Requires-Dist: h5py
Requires-Dist: docutils (>=0.3)
